{"suspect_bot_list":[
{"user_id": 879543960292671500, "user_name": "Rohit Reddy Gaddam", "followers": 11, "followees": 128},
{"user_id": 893010576862871600, "user_name": "Ejsophiakelly", "followers": 8, "followees": 125},
{"user_id": 890861009946034200, "user_name": "M.J. Hudson", "followers": 12, "followees": 174},
{"user_id": 893413053303144400, "user_name": "Tip Star", "followers": 104, "followees": 1213},
{"user_id": 797298663777153000, "user_name": "Mary Stanley", "followers": 10, "followees": 250},
{"user_id": 893338364631367700, "user_name": "Max Alexander", "followers": 63, "followees": 1372},
{"user_id": 894753059254841300, "user_name": "Triestina", "followers": 13, "followees": 232},
{"user_id": 721373044258701300, "user_name": "Ethan", "followers": 26, "followees": 499},
{"user_id": 2453956351, "user_name": "\u3042(\u30a4\u30e9\u30a4\u30e9)", "followers": 95, "followees": 1034},
{"user_id": 276352088, "user_name": "Jade Ward", "followers": 14, "followees": 405},
{"user_id": 311934646, "user_name": "Paula Oldridge", "followers": 12, "followees": 387},
{"user_id": 888674992837099500, "user_name": "strawhat_93", "followers": 28, "followees": 375},
{"user_id": 834949337620725800, "user_name": "Leadback", "followers": 96, "followees": 1586},
{"user_id": 771195986592936000, "user_name": "colombiano", "followers": 8, "followees": 192},
{"user_id": 902000140147466200, "user_name": "TT", "followers": 7, "followees": 188},
{"user_id": 2548725500, "user_name": "Scott Rowntree", "followers": 20, "followees": 286},
{"user_id": 900873026480230400, "user_name": "HusbandsOfMelbourne", "followers": 26, "followees": 337},
{"user_id": 793945680557416400, "user_name": "\ud83d\ude0d", "followers": 6, "followees": 107},
{"user_id": 858669794144288800, "user_name": "Wotton Lang", "followers": 47, "followees": 642},
{"user_id": 3864148572, "user_name": "simon couch", "followers": 32, "followees": 569},
{"user_id": 895804746002382800, "user_name": "Tristan", "followers": 30, "followees": 427},
{"user_id": 903450311863369700, "user_name": "dali_22", "followers": 13, "followees": 247},
{"user_id": 2715384288, "user_name": "#Lesley", "followers": 19, "followees": 282},
{"user_id": 875730857893347300, "user_name": "Ash_ley.", "followers": 101, "followees": 1177},
{"user_id": 4901979200, "user_name": "Christian", "followers": 13, "followees": 148},
{"user_id": 1617412170, "user_name": "Mmk", "followers": 18, "followees": 280},
{"user_id": 897579512866652200, "user_name": "Thsau", "followers": 8, "followees": 123},
{"user_id": 98150584, "user_name": "Nish", "followers": 103, "followees": 1097},
{"user_id": 891308224187572200, "user_name": "Sheree", "followers": 16, "followees": 223},
{"user_id": 897651168456736800, "user_name": "Francis Moore", "followers": 13, "followees": 330},
{"user_id": 706849849753272300, "user_name": "\u307d\u3076\u305f", "followers": 14, "followees": 254},
{"user_id": 906712414627835900, "user_name": "Harry", "followers": 47, "followees": 617},
{"user_id": 2602852878, "user_name": "jack", "followers": 79, "followees": 1341},
{"user_id": 901385391638421500, "user_name": "Cameron Lucas", "followers": 90, "followees": 990},
{"user_id": 828503392452370400, "user_name": "Jack Wilder", "followers": 15, "followees": 212},
{"user_id": 750101881679077400, "user_name": "Colette Jurczyk", "followers": 13, "followees": 204},
{"user_id": 914560902913052700, "user_name": "ychauhan", "followers": 11, "followees": 176},
{"user_id": 728603324837077000, "user_name": "\ud83c\uddef\ud83c\uddf5\u5ca9\u592a\u90ce", "followers": 21, "followees": 249},
{"user_id": 1415673270, "user_name": "AJ \ud83c\udde6\ud83c\uddfa\ud83c\uddf5\ud83c\udded", "followers": 155, "followees": 1664},
{"user_id": 884367110, "user_name": "Horndady67 \ud83c\udde6\ud83c\uddfa", "followers": 20, "followees": 877},
{"user_id": 919429583132229600, "user_name": "Garth Dandy", "followers": 30, "followees": 367},
{"user_id": 174941227, "user_name": "S\u541b", "followers": 36, "followees": 498},
{"user_id": 841159395220176900, "user_name": "Sunil Sathyanarayana", "followers": 23, "followees": 283},
{"user_id": 732216995005927400, "user_name": "Arnav Singh", "followers": 41, "followees": 454},
{"user_id": 933978415413076000, "user_name": "Kim", "followers": 80, "followees": 5000},
{"user_id": 153712107, "user_name": "Samy ANGEL", "followers": 20, "followees": 329},
{"user_id": 901706640763662300, "user_name": "AC1 Aweiss Mirza", "followers": 4, "followees": 131},
{"user_id": 816097246613676000, "user_name": "Sarah Kaddour", "followers": 27, "followees": 420},
{"user_id": 45390455, "user_name": "Graham Cant", "followers": 20, "followees": 202},
{"user_id": 823473433568608300, "user_name": "Zach_am", "followers": 8, "followees": 125},
{"user_id": 885300158597972000, "user_name": "hideo kojima wishes he was yoko taro", "followers": 11, "followees": 144},
{"user_id": 835459882635579400, "user_name": "EliteGutrunner24", "followers": 24, "followees": 310},
{"user_id": 893221979716599800, "user_name": "Liam J.M", "followers": 11, "followees": 143},
{"user_id": 870375131343802400, "user_name": "Mr Coverage", "followers": 13, "followees": 162},
{"user_id": 89040710, "user_name": "Pete de Vries", "followers": 236, "followees": 2370},
{"user_id": 873159096878284800, "user_name": "Hercule Poirot", "followers": 20, "followees": 282},
{"user_id": 1485828217, "user_name": "DavidPeterMeier", "followers": 7, "followees": 354},
{"user_id": 740289014, "user_name": "Chris Grima\u2122", "followers": 19, "followees": 241},
{"user_id": 910537053867098100, "user_name": "Nick Katsilis", "followers": 158, "followees": 2719},
{"user_id": 781986176966225900, "user_name": "Jack", "followers": 72, "followees": 860},
{"user_id": 757738541262643200, "user_name": "depression napTM", "followers": 100, "followees": 1106},
{"user_id": 916545085944225800, "user_name": "John Cosstick", "followers": 8, "followees": 146},
{"user_id": 845993792297562100, "user_name": "Will Newby", "followers": 64, "followees": 852},
{"user_id": 913300719482019800, "user_name": "sarah kate", "followers": 12, "followees": 180},
{"user_id": 857604183423189000, "user_name": "meat", "followers": 19, "followees": 212},
{"user_id": 909053556199587800, "user_name": "Mister.Z", "followers": 6, "followees": 103},
{"user_id": 794835976916828200, "user_name": "Jack Belcher", "followers": 21, "followees": 332},
{"user_id": 282901680, "user_name": "goraya", "followers": 17, "followees": 263},
{"user_id": 187333593, "user_name": "G. McP", "followers": 45, "followees": 565},
{"user_id": 866672377911849000, "user_name": "calamari", "followers": 29, "followees": 502},
{"user_id": 848356365076529200, "user_name": "Dermot", "followers": 10, "followees": 136},
{"user_id": 3392250739, "user_name": "Michel Vallance", "followers": 68, "followees": 844},
{"user_id": 350154185, "user_name": "Your Friendly Neighbourhood Aura", "followers": 48, "followees": 581},
{"user_id": 564272860, "user_name": "ohwellwhatevernevermind", "followers": 25, "followees": 345},
{"user_id": 418337550, "user_name": "Maggie Muir", "followers": 63, "followees": 665},
{"user_id": 732942607358132200, "user_name": "desiologydj", "followers": 39, "followees": 441},
{"user_id": 913183601943965700, "user_name": "VikAgainstTheWorld", "followers": 26, "followees": 426},
{"user_id": 435867824, "user_name": "adstheo", "followers": 56, "followees": 911},
{"user_id": 32980366, "user_name": "Ankur Patel", "followers": 114, "followees": 1587},
{"user_id": 1261509511, "user_name": "andy", "followers": 55, "followees": 2037},
{"user_id": 888999624203149300, "user_name": "Tongu Eincheek", "followers": 16, "followees": 189},
{"user_id": 773028706730119200, "user_name": "Connor W. Evans \ud83d\udc8e", "followers": 41, "followees": 1426},
{"user_id": 360434186, "user_name": "leigh harrison", "followers": 66, "followees": 713},
{"user_id": 955153829917474800, "user_name": "parots", "followers": 14, "followees": 167},
{"user_id": 1079276257, "user_name": "Harry, from the house of stale memes", "followers": 138, "followees": 1556},
{"user_id": 740431678632558600, "user_name": "YSKR", "followers": 16, "followees": 564},
{"user_id": 764369646564671500, "user_name": "rach_rich", "followers": 10, "followees": 131},
{"user_id": 715073959142633500, "user_name": "Beilul", "followers": 25, "followees": 449},
{"user_id": 823461905884774400, "user_name": "Shayne", "followers": 13, "followees": 250},
{"user_id": 960520051739779100, "user_name": "Victor Wong", "followers": 9, "followees": 166},
{"user_id": 830713672829800400, "user_name": "Brodie Cowburn", "followers": 64, "followees": 1133},
{"user_id": 24598450, "user_name": "Lachlan Martin", "followers": 186, "followees": 2447},
{"user_id": 931608761860464600, "user_name": "Ikhwan Retro XIX Warrior", "followers": 17, "followees": 396},
{"user_id": 461457832, "user_name": "Phil Sherrill", "followers": 31, "followees": 350},
{"user_id": 948703822884479000, "user_name": "Smart Putter", "followers": 85, "followees": 2904},
{"user_id": 876074280554946600, "user_name": "introvert \u2744\ufe0f", "followers": 2, "followees": 113},
{"user_id": 808060782252466200, "user_name": "Dale Fitzhenry", "followers": 11, "followees": 204},
{"user_id": 780309697693782000, "user_name": "Mitchell Jack Trewin", "followers": 10, "followees": 102},
{"user_id": 938809806256771100, "user_name": "JacquelineVictoriaReilly", "followers": 140, "followees": 1941}],
"total_users":99}